pyflexebs/__init__.py
pyflexebs/configs.py
pyflexebs/main.py
pyflexebs/static.py
pyflexebs/utils.py
pyflexebs-0.0.89.dist-info/LICENSE
pyflexebs-0.0.89.dist-info/METADATA
pyflexebs-0.0.89.dist-info/WHEEL
pyflexebs-0.0.89.dist-info/entry_points.txt
pyflexebs-0.0.89.dist-info/top_level.txt
pyflexebs-0.0.89.dist-info/RECORD
