Metadata-Version: 2.1
Name: pyflexebs
Version: 0.0.89
Summary: Pyflexebs will allow you to monitor and expand/contract you EBS volumes in aws
Home-page: https://veltzer.github.io/pyflexebs
Download-URL: https://github.com/veltzer/pyflexebs
Author: Mark Veltzer
Author-email: mark.veltzer@gmail.com
Maintainer: Mark Veltzer
Maintainer-email: mark.veltzer@gmail.com
License: MIT
Keywords: aws,ebs
Platform: python3
Classifier: Development Status :: 4 - Beta
Classifier: Environment :: Console
Classifier: Operating System :: OS Independent
Classifier: Programming Language :: Python
Classifier: Programming Language :: Python :: 3
Classifier: Programming Language :: Python :: 3 :: Only
Classifier: Programming Language :: Python :: 3.11
Classifier: Topic :: Utilities
Classifier: License :: OSI Approved :: MIT License
License-File: LICENSE
Requires-Dist: pytconf
Requires-Dist: pylogconf
Requires-Dist: psutil
Requires-Dist: boto3
Requires-Dist: boto3-stubs
Requires-Dist: pyfakeuse
Requires-Dist: ec2-metadata
Requires-Dist: pypathutil
Requires-Dist: hurry.filesize
Requires-Dist: bitmath
Requires-Dist: python-daemon
